[
  {
    "title": "After 8 years dumping billions of XRP, Jed McCaleb's stack runs...",
    "subTitle": "New York,  22 Agust 2022 ",
    "date": "Jan. 21, 2022",
    "name": "JORDAN FINNESETH",
    "image": "/image/rectangle.png"
  },
  {
    "title": "Contagion: Genesis faces huge losses, BlockFi's $1B loan,...",
    "subTitle": "New York,  22 Agust 2022 ",
    "date": "Jan. 21, 2022",
    "name": "JORDAN FINNESETH",
    "image": "/image/rectangle.png"
  },
  {
    "title": "Nifty news: Sandbox LAND on Polygon, ETH gain a tax loss and...",
    "subTitle": "New York,  22 Agust 2022 ",
    "date": "Jan. 21, 2022",
    "name": "JORDAN FINNESETH",
    "image": "/image/rectangle.png"
  },
  {
    "title": "EU officials reach agreement on AML authority for supervising...",
    "subTitle": "New York,  22 Agust 2022 ",
    "date": "Jan. 21, 2022",
    "name": "JORDAN FINNESETH",
    "image": "/image/rectangle.png"
  }
]
